dmt_learn/__init__.py
dmt_learn/dmt_learn.py
dmt_learn/load_data.py
dmt_learn/call_backs/EvalAcc_high_low_emb.py
dmt_learn/call_backs/MaskExp.py
dmt_learn/call_backs/__init__.py
dmt_learn/data_model/__init__.py
dmt_learn/data_model/datamodel_tri_test.py
dmt_learn/data_model/dataset_all.py
dmt_learn/data_model/dataset_bio.py
dmt_learn/data_model/dataset_cifar.py
dmt_learn/data_model/dataset_meta.py
dmt_learn/data_model/dataset_nist.py
dmt_learn/data_model/dataset_text.py
dmt_learn/eval/__init__.py
dmt_learn/eval/eval_core.py
dmt_learn/eval/eval_core_base.py
dmt_learn/eval/evaluation.py
dmt_learn/manifolds/__init__.py
dmt_learn/manifolds/base.py
dmt_learn/manifolds/euclidean.py
dmt_learn/manifolds/hyperbolic_project.py
dmt_learn/manifolds/hyperboloid.py
dmt_learn/manifolds/math_utils.py
dmt_learn/manifolds/poincare.py
dmt_learn/model/__init__.py
dmt_learn/model/nnet.py
dmt_learn/model/nnet_new_exp.py
dmt_learn/model/nnet_new_exp_mix_in_lat_exp_all.py
dmt_learn/model/resnet.py
dmt_learn-0.0.81.dist-info/METADATA
dmt_learn-0.0.81.dist-info/WHEEL
dmt_learn-0.0.81.dist-info/top_level.txt
dmt_learn-0.0.81.dist-info/RECORD
