Metadata-Version: 2.1
Name: dmt-learn
Version: 0.0.81
Summary: dmt learn package
Home-page: https://github.com/yourusername/my_package
Author: Zelin Zang
Author-email: zangzelin@westlake.edu.cn
Classifier: Programming Language :: Python :: 3
Classifier: License :: OSI Approved :: MIT License
Classifier: Operating System :: OS Independent
Requires-Python: >=3.10
Requires-Dist: numpy >=1.21.0
Requires-Dist: plotly
Requires-Dist: scikit-learn
Requires-Dist: pandas
Requires-Dist: lightning
Requires-Dist: wandb
Requires-Dist: munkres
Requires-Dist: umap-learn
Requires-Dist: scanpy
Requires-Dist: kaleido
Requires-Dist: transformers
